<?xml version="1.0" encoding="utf-8"?>
<permissions>
    <privapp-permissions package="com.oplus.camera" >
        <permission name="android.permission.SYSTEM_CAMERA" fixed="true" />
        <permission name="android.permission.CAMERA_OPEN_CLOSE_LISTENER" fixed="true" />
        <permission name="android.permission.CAMERA" fixed="true" />
        <permission name="android.permission.RECORD_AUDIO" fixed="true" />
        <permission name="android.permission.WRITE_EXTERNAL_STORAGE" fixed="true" />
        <permission name="android.permission.READ_EXTERNAL_STORAGE" fixed="true" />
        <permission name="android.permission.READ_PHONE_STATE" fixed="true" />
     </privapp-permissions>

     <privapp-permissions package="com.oplus.customize.coreapp">
        <permission name="android.permission.READ_PRIVILEGED_PHONE_STATE" />
        <permission name="android.permission.REBOOT"/>
        <permission name="android.permission.MANAGE_USERS"/>
    </privapp-permissions>
</permissions>
